RachelCore
