Metadata-Version: 2.1
Name: RachelCore
Version: 0.0.4
Summary: Rachel assistant core.
Home-page: https://github.com/BlackIQ/RachelCore
Author: Amirhossein Mohammadi
Author-email: amirhosseinmohammadi1380@yahoo.com
License: MIT
Platform: UNKNOWN
License-File: LICENSE
